{
    "imgHeight": 1024, 
    "imgWidth": 2048, 
    "objects": [
        {
            "label": "vegetation", 
            "polygon": [
                [
                    -1, 
                    0
                ], 
                [
                    2045, 
                    1
                ], 
                [
                    2045, 
                    538
                ], 
                [
                    0, 
                    646
                ]
            ]
        }, 
        {
            "label": "terrain", 
            "polygon": [
                [
                    0, 
                    630
                ], 
                [
                    121, 
                    635
                ], 
                [
                    228, 
                    637
                ], 
                [
                    367, 
                    582
                ], 
                [
                    502, 
                    548
                ], 
                [
                    645, 
                    534
                ], 
                [
                    976, 
                    521
                ], 
                [
                    1443, 
                    506
                ], 
                [
                    1699, 
                    494
                ], 
                [
                    1877, 
                    487
                ], 
                [
                    2045, 
                    476
                ], 
                [
                    2044, 
                    1022
                ], 
                [
                    0, 
                    1021
                ]
            ]
        }, 
        {
            "label": "building", 
            "polygon": [
                [
                    1900, 
                    293
                ], 
                [
                    1738, 
                    355
                ], 
                [
                    1743, 
                    491
                ], 
                [
                    1830, 
                    492
                ], 
                [
                    2045, 
                    485
                ], 
                [
                    2045, 
                    322
                ], 
                [
                    2009, 
                    313
                ], 
                [
                    1979, 
                    325
                ], 
                [
                    1958, 
                    317
                ], 
                [
                    1925, 
                    311
                ], 
                [
                    1917, 
                    298
                ]
            ]
        }, 
        {
            "label": "pole", 
            "polygon": [
                [
                    16, 
                    517
                ], 
                [
                    19, 
                    631
                ], 
                [
                    22, 
                    631
                ], 
                [
                    20, 
                    518
                ]
            ]
        }, 
        {
            "label": "pole", 
            "polygon": [
                [
                    249, 
                    644
                ], 
                [
                    238, 
                    388
                ], 
                [
                    240, 
                    388
                ], 
                [
                    254, 
                    643
                ]
            ]
        }, 
        {
            "label": "pole", 
            "polygon": [
                [
                    196, 
                    387
                ], 
                [
                    213, 
                    374
                ], 
                [
                    247, 
                    381
                ], 
                [
                    249, 
                    390
                ]
            ]
        }, 
        {
            "label": "sidewalk", 
            "polygon": [
                [
                    20, 
                    683
                ], 
                [
                    159, 
                    706
                ], 
                [
                    242, 
                    722
                ], 
                [
                    303, 
                    728
                ], 
                [
                    344, 
                    734
                ], 
                [
                    353, 
                    740
                ], 
                [
                    346, 
                    751
                ], 
                [
                    260, 
                    788
                ], 
                [
                    137, 
                    834
                ], 
                [
                    65, 
                    856
                ], 
                [
                    -2, 
                    868
                ], 
                [
                    0, 
                    1020
                ], 
                [
                    2044, 
                    1021
                ], 
                [
                    2045, 
                    729
                ], 
                [
                    1235, 
                    692
                ], 
                [
                    734, 
                    674
                ], 
                [
                    356, 
                    660
                ], 
                [
                    -1, 
                    646
                ], 
                [
                    -2, 
                    682
                ]
            ]
        }, 
        {
            "label": "ground", 
            "polygon": [
                [
                    989, 
                    535
                ], 
                [
                    1007, 
                    542
                ], 
                [
                    1136, 
                    537
                ], 
                [
                    1210, 
                    527
                ], 
                [
                    1273, 
                    532
                ], 
                [
                    1366, 
                    526
                ], 
                [
                    1489, 
                    521
                ], 
                [
                    1598, 
                    514
                ], 
                [
                    1713, 
                    509
                ], 
                [
                    1806, 
                    506
                ], 
                [
                    1811, 
                    503
                ], 
                [
                    1668, 
                    506
                ], 
                [
                    1546, 
                    510
                ], 
                [
                    1453, 
                    513
                ], 
                [
                    1320, 
                    516
                ], 
                [
                    1255, 
                    513
                ], 
                [
                    1164, 
                    517
                ], 
                [
                    1081, 
                    521
                ], 
                [
                    1040, 
                    523
                ], 
                [
                    1008, 
                    526
                ]
            ]
        }, 
        {
            "label": "pole", 
            "polygon": [
                [
                    782, 
                    184
                ], 
                [
                    802, 
                    645
                ], 
                [
                    813, 
                    643
                ], 
                [
                    791, 
                    187
                ]
            ]
        }, 
        {
            "label": "pole", 
            "polygon": [
                [
                    797, 
                    190
                ], 
                [
                    796, 
                    173
                ], 
                [
                    767, 
                    169
                ], 
                [
                    755, 
                    163
                ], 
                [
                    738, 
                    161
                ], 
                [
                    724, 
                    172
                ], 
                [
                    717, 
                    184
                ], 
                [
                    777, 
                    191
                ]
            ]
        }, 
        {
            "label": "pole", 
            "polygon": [
                [
                    815, 
                    301
                ], 
                [
                    834, 
                    719
                ], 
                [
                    847, 
                    719
                ], 
                [
                    827, 
                    305
                ]
            ]
        }, 
        {
            "label": "traffic sign", 
            "polygon": [
                [
                    858, 
                    264
                ], 
                [
                    843, 
                    241
                ], 
                [
                    817, 
                    235
                ], 
                [
                    796, 
                    241
                ], 
                [
                    790, 
                    256
                ], 
                [
                    789, 
                    282
                ], 
                [
                    804, 
                    304
                ], 
                [
                    816, 
                    313
                ], 
                [
                    840, 
                    311
                ], 
                [
                    856, 
                    294
                ], 
                [
                    858, 
                    276
                ]
            ]
        }, 
        {
            "label": "bicycle", 
            "polygon": [
                [
                    1133, 
                    478
                ], 
                [
                    1136, 
                    440
                ], 
                [
                    1113, 
                    448
                ], 
                [
                    1101, 
                    462
                ], 
                [
                    1085, 
                    481
                ], 
                [
                    1073, 
                    470
                ], 
                [
                    1073, 
                    464
                ], 
                [
                    1088, 
                    460
                ], 
                [
                    1088, 
                    455
                ], 
                [
                    1073, 
                    457
                ], 
                [
                    1068, 
                    463
                ], 
                [
                    1060, 
                    462
                ], 
                [
                    1056, 
                    470
                ], 
                [
                    1054, 
                    478
                ], 
                [
                    1062, 
                    475
                ], 
                [
                    1065, 
                    479
                ], 
                [
                    1056, 
                    483
                ], 
                [
                    1055, 
                    489
                ], 
                [
                    1048, 
                    495
                ], 
                [
                    1043, 
                    511
                ], 
                [
                    1047, 
                    523
                ], 
                [
                    1056, 
                    533
                ], 
                [
                    1061, 
                    538
                ], 
                [
                    1079, 
                    538
                ], 
                [
                    1088, 
                    534
                ], 
                [
                    1090, 
                    529
                ], 
                [
                    1097, 
                    523
                ], 
                [
                    1104, 
                    526
                ], 
                [
                    1111, 
                    524
                ], 
                [
                    1116, 
                    531
                ], 
                [
                    1122, 
                    537
                ], 
                [
                    1143, 
                    535
                ], 
                [
                    1149, 
                    529
                ], 
                [
                    1149, 
                    513
                ], 
                [
                    1145, 
                    500
                ], 
                [
                    1139, 
                    491
                ], 
                [
                    1134, 
                    485
                ]
            ]
        }, 
        {
            "label": "pole", 
            "polygon": [
                [
                    1482, 
                    261
                ], 
                [
                    1495, 
                    512
                ], 
                [
                    1484, 
                    513
                ], 
                [
                    1474, 
                    261
                ]
            ]
        }, 
        {
            "label": "static", 
            "polygon": [
                [
                    1713, 
                    211
                ], 
                [
                    1566, 
                    285
                ], 
                [
                    1427, 
                    253
                ], 
                [
                    1258, 
                    287
                ], 
                [
                    1084, 
                    263
                ], 
                [
                    1084, 
                    266
                ], 
                [
                    1255, 
                    292
                ], 
                [
                    1422, 
                    258
                ], 
                [
                    1429, 
                    259
                ], 
                [
                    1565, 
                    291
                ], 
                [
                    1713, 
                    217
                ]
            ]
        }, 
        {
            "label": "pole", 
            "polygon": [
                [
                    1072, 
                    239
                ], 
                [
                    1088, 
                    536
                ], 
                [
                    1100, 
                    536
                ], 
                [
                    1085, 
                    238
                ]
            ]
        }, 
        {
            "label": "static", 
            "polygon": [
                [
                    905, 
                    554
                ], 
                [
                    1086, 
                    267
                ], 
                [
                    1086, 
                    270
                ], 
                [
                    908, 
                    554
                ]
            ]
        }, 
        {
            "label": "static", 
            "polygon": [
                [
                    875, 
                    539
                ], 
                [
                    1074, 
                    276
                ], 
                [
                    1074, 
                    279
                ], 
                [
                    879, 
                    539
                ]
            ]
        }, 
        {
            "label": "pole", 
            "polygon": [
                [
                    1261, 
                    451
                ], 
                [
                    1255, 
                    286
                ], 
                [
                    1257, 
                    286
                ], 
                [
                    1263, 
                    455
                ]
            ]
        }, 
        {
            "label": "static", 
            "polygon": [
                [
                    1242, 
                    461
                ], 
                [
                    1240, 
                    468
                ], 
                [
                    1243, 
                    475
                ], 
                [
                    1263, 
                    475
                ], 
                [
                    1283, 
                    474
                ], 
                [
                    1285, 
                    467
                ], 
                [
                    1282, 
                    460
                ], 
                [
                    1269, 
                    460
                ]
            ]
        }, 
        {
            "label": "person", 
            "polygon": [
                [
                    1248, 
                    417
                ], 
                [
                    1243, 
                    421
                ], 
                [
                    1242, 
                    427
                ], 
                [
                    1244, 
                    432
                ], 
                [
                    1243, 
                    437
                ], 
                [
                    1242, 
                    446
                ], 
                [
                    1245, 
                    455
                ], 
                [
                    1252, 
                    460
                ], 
                [
                    1259, 
                    461
                ], 
                [
                    1260, 
                    460
                ], 
                [
                    1264, 
                    465
                ], 
                [
                    1270, 
                    471
                ], 
                [
                    1274, 
                    470
                ], 
                [
                    1277, 
                    463
                ], 
                [
                    1277, 
                    458
                ], 
                [
                    1283, 
                    462
                ], 
                [
                    1287, 
                    465
                ], 
                [
                    1290, 
                    466
                ], 
                [
                    1297, 
                    461
                ], 
                [
                    1300, 
                    455
                ], 
                [
                    1292, 
                    458
                ], 
                [
                    1286, 
                    454
                ], 
                [
                    1276, 
                    449
                ], 
                [
                    1264, 
                    447
                ], 
                [
                    1264, 
                    445
                ], 
                [
                    1268, 
                    445
                ], 
                [
                    1269, 
                    443
                ], 
                [
                    1266, 
                    438
                ], 
                [
                    1262, 
                    435
                ], 
                [
                    1260, 
                    434
                ], 
                [
                    1258, 
                    428
                ], 
                [
                    1262, 
                    423
                ], 
                [
                    1259, 
                    421
                ], 
                [
                    1254, 
                    417
                ]
            ]
        }, 
        {
            "label": "static", 
            "polygon": [
                [
                    1430, 
                    266
                ], 
                [
                    1454, 
                    301
                ], 
                [
                    1479, 
                    284
                ], 
                [
                    1478, 
                    280
                ], 
                [
                    1455, 
                    296
                ], 
                [
                    1429, 
                    260
                ]
            ]
        }, 
        {
            "label": "pole", 
            "polygon": [
                [
                    1455, 
                    446
                ], 
                [
                    1457, 
                    298
                ], 
                [
                    1454, 
                    299
                ], 
                [
                    1453, 
                    440
                ]
            ]
        }, 
        {
            "label": "person", 
            "polygon": [
                [
                    1435, 
                    421
                ], 
                [
                    1441, 
                    417
                ], 
                [
                    1446, 
                    417
                ], 
                [
                    1451, 
                    422
                ], 
                [
                    1453, 
                    429
                ], 
                [
                    1454, 
                    433
                ], 
                [
                    1458, 
                    432
                ], 
                [
                    1458, 
                    435
                ], 
                [
                    1455, 
                    440
                ], 
                [
                    1458, 
                    444
                ], 
                [
                    1462, 
                    446
                ], 
                [
                    1464, 
                    448
                ], 
                [
                    1468, 
                    448
                ], 
                [
                    1472, 
                    447
                ], 
                [
                    1474, 
                    452
                ], 
                [
                    1473, 
                    456
                ], 
                [
                    1435, 
                    457
                ]
            ]
        }, 
        {
            "label": "static", 
            "polygon": [
                [
                    1437, 
                    469
                ], 
                [
                    1475, 
                    468
                ], 
                [
                    1476, 
                    460
                ], 
                [
                    1472, 
                    454
                ], 
                [
                    1435, 
                    454
                ]
            ]
        }, 
        {
            "label": "pole", 
            "polygon": [
                [
                    1419, 
                    208
                ], 
                [
                    1424, 
                    514
                ], 
                [
                    1439, 
                    513
                ], 
                [
                    1432, 
                    208
                ], 
                [
                    1425, 
                    206
                ]
            ]
        }, 
        {
            "label": "person", 
            "polygon": [
                [
                    1562, 
                    417
                ], 
                [
                    1561, 
                    407
                ], 
                [
                    1557, 
                    403
                ], 
                [
                    1548, 
                    406
                ], 
                [
                    1546, 
                    410
                ], 
                [
                    1548, 
                    418
                ], 
                [
                    1548, 
                    421
                ], 
                [
                    1542, 
                    429
                ], 
                [
                    1536, 
                    439
                ], 
                [
                    1537, 
                    444
                ], 
                [
                    1547, 
                    445
                ], 
                [
                    1543, 
                    453
                ], 
                [
                    1541, 
                    462
                ], 
                [
                    1544, 
                    480
                ], 
                [
                    1547, 
                    499
                ], 
                [
                    1548, 
                    511
                ], 
                [
                    1544, 
                    515
                ], 
                [
                    1545, 
                    518
                ], 
                [
                    1555, 
                    516
                ], 
                [
                    1559, 
                    511
                ], 
                [
                    1557, 
                    496
                ], 
                [
                    1556, 
                    479
                ], 
                [
                    1564, 
                    502
                ], 
                [
                    1567, 
                    511
                ], 
                [
                    1563, 
                    516
                ], 
                [
                    1569, 
                    517
                ], 
                [
                    1578, 
                    513
                ], 
                [
                    1574, 
                    495
                ], 
                [
                    1570, 
                    479
                ], 
                [
                    1569, 
                    462
                ], 
                [
                    1567, 
                    452
                ], 
                [
                    1570, 
                    429
                ], 
                [
                    1569, 
                    423
                ], 
                [
                    1566, 
                    421
                ]
            ]
        }, 
        {
            "label": "pole", 
            "polygon": [
                [
                    1564, 
                    281
                ], 
                [
                    1580, 
                    467
                ], 
                [
                    1582, 
                    467
                ], 
                [
                    1566, 
                    281
                ]
            ]
        }, 
        {
            "label": "static", 
            "polygon": [
                [
                    1600, 
                    461
                ], 
                [
                    1569, 
                    464
                ], 
                [
                    1561, 
                    466
                ], 
                [
                    1556, 
                    468
                ], 
                [
                    1558, 
                    481
                ], 
                [
                    1573, 
                    481
                ], 
                [
                    1596, 
                    479
                ], 
                [
                    1599, 
                    478
                ]
            ]
        }, 
        {
            "label": "person", 
            "polygon": [
                [
                    1628, 
                    463
                ], 
                [
                    1629, 
                    447
                ], 
                [
                    1622, 
                    426
                ], 
                [
                    1620, 
                    414
                ], 
                [
                    1612, 
                    402
                ], 
                [
                    1608, 
                    398
                ], 
                [
                    1609, 
                    391
                ], 
                [
                    1606, 
                    385
                ], 
                [
                    1598, 
                    383
                ], 
                [
                    1590, 
                    387
                ], 
                [
                    1590, 
                    393
                ], 
                [
                    1589, 
                    401
                ], 
                [
                    1593, 
                    406
                ], 
                [
                    1588, 
                    412
                ], 
                [
                    1584, 
                    425
                ], 
                [
                    1576, 
                    424
                ], 
                [
                    1571, 
                    427
                ], 
                [
                    1574, 
                    433
                ], 
                [
                    1574, 
                    437
                ], 
                [
                    1577, 
                    442
                ], 
                [
                    1583, 
                    444
                ], 
                [
                    1587, 
                    438
                ], 
                [
                    1594, 
                    431
                ], 
                [
                    1597, 
                    434
                ], 
                [
                    1599, 
                    451
                ], 
                [
                    1598, 
                    461
                ], 
                [
                    1597, 
                    480
                ], 
                [
                    1601, 
                    492
                ], 
                [
                    1604, 
                    506
                ], 
                [
                    1603, 
                    515
                ], 
                [
                    1613, 
                    514
                ], 
                [
                    1613, 
                    504
                ], 
                [
                    1612, 
                    488
                ], 
                [
                    1616, 
                    473
                ], 
                [
                    1620, 
                    491
                ], 
                [
                    1625, 
                    505
                ], 
                [
                    1625, 
                    514
                ], 
                [
                    1635, 
                    513
                ], 
                [
                    1636, 
                    501
                ], 
                [
                    1632, 
                    490
                ], 
                [
                    1628, 
                    478
                ]
            ]
        }, 
        {
            "label": "static", 
            "polygon": [
                [
                    1722, 
                    218
                ], 
                [
                    1991, 
                    485
                ], 
                [
                    1986, 
                    485
                ], 
                [
                    1722, 
                    222
                ]
            ]
        }, 
        {
            "label": "pole", 
            "polygon": [
                [
                    1709, 
                    187
                ], 
                [
                    1719, 
                    503
                ], 
                [
                    1735, 
                    503
                ], 
                [
                    1723, 
                    185
                ], 
                [
                    1720, 
                    183
                ], 
                [
                    1713, 
                    182
                ]
            ]
        }, 
        {
            "label": "static", 
            "polygon": [
                [
                    1719, 
                    229
                ], 
                [
                    1864, 
                    492
                ], 
                [
                    1860, 
                    492
                ], 
                [
                    1719, 
                    236
                ]
            ]
        }, 
        {
            "label": "ego vehicle", 
            "polygon": [
                [
                    271, 
                    1023
                ], 
                [
                    387, 
                    1009
                ], 
                [
                    549, 
                    993
                ], 
                [
                    821, 
                    966
                ], 
                [
                    1082, 
                    950
                ], 
                [
                    1142, 
                    947
                ], 
                [
                    1112, 
                    932
                ], 
                [
                    1096, 
                    896
                ], 
                [
                    1108, 
                    861
                ], 
                [
                    1137, 
                    844
                ], 
                [
                    1175, 
                    844
                ], 
                [
                    1204, 
                    867
                ], 
                [
                    1209, 
                    897
                ], 
                [
                    1195, 
                    931
                ], 
                [
                    1161, 
                    945
                ], 
                [
                    1376, 
                    957
                ], 
                [
                    1654, 
                    977
                ], 
                [
                    1883, 
                    1002
                ], 
                [
                    2028, 
                    1023
                ]
            ]
        }, 
        {
            "label": "out of roi", 
            "polygon": [
                [
                    0, 
                    0
                ], 
                [
                    2048, 
                    0
                ], 
                [
                    2048, 
                    1024
                ], 
                [
                    0, 
                    1024
                ], 
                [
                    0, 
                    0
                ], 
                [
                    5, 
                    5
                ], 
                [
                    5, 
                    1019
                ], 
                [
                    2043, 
                    1019
                ], 
                [
                    2043, 
                    5
                ], 
                [
                    5, 
                    5
                ]
            ]
        }
    ]
}