{
    "imgHeight": 1024, 
    "imgWidth": 2048, 
    "objects": [
        {
            "label": "sky", 
            "polygon": [
                [
                    1093, 
                    0
                ], 
                [
                    1447, 
                    1
                ], 
                [
                    1421, 
                    289
                ], 
                [
                    1108, 
                    266
                ]
            ]
        }, 
        {
            "label": "vegetation", 
            "polygon": [
                [
                    855, 
                    0
                ], 
                [
                    1188, 
                    0
                ], 
                [
                    1194, 
                    9
                ], 
                [
                    1192, 
                    33
                ], 
                [
                    1196, 
                    42
                ], 
                [
                    1207, 
                    28
                ], 
                [
                    1223, 
                    23
                ], 
                [
                    1238, 
                    23
                ], 
                [
                    1249, 
                    33
                ], 
                [
                    1257, 
                    49
                ], 
                [
                    1281, 
                    48
                ], 
                [
                    1295, 
                    33
                ], 
                [
                    1300, 
                    41
                ], 
                [
                    1296, 
                    54
                ], 
                [
                    1309, 
                    63
                ], 
                [
                    1315, 
                    61
                ], 
                [
                    1310, 
                    44
                ], 
                [
                    1310, 
                    34
                ], 
                [
                    1322, 
                    40
                ], 
                [
                    1329, 
                    52
                ], 
                [
                    1344, 
                    42
                ], 
                [
                    1370, 
                    35
                ], 
                [
                    1380, 
                    418
                ], 
                [
                    824, 
                    400
                ]
            ]
        }, 
        {
            "label": "building", 
            "polygon": [
                [
                    931, 
                    218
                ], 
                [
                    1010, 
                    200
                ], 
                [
                    1010, 
                    173
                ], 
                [
                    988, 
                    163
                ], 
                [
                    992, 
                    157
                ], 
                [
                    1163, 
                    125
                ], 
                [
                    1339, 
                    141
                ], 
                [
                    1382, 
                    205
                ], 
                [
                    1370, 
                    427
                ], 
                [
                    985, 
                    423
                ], 
                [
                    980, 
                    231
                ]
            ]
        }, 
        {
            "label": "vegetation", 
            "polygon": [
                [
                    863, 
                    237
                ], 
                [
                    883, 
                    223
                ], 
                [
                    894, 
                    219
                ], 
                [
                    912, 
                    225
                ], 
                [
                    931, 
                    235
                ], 
                [
                    950, 
                    245
                ], 
                [
                    961, 
                    246
                ], 
                [
                    968, 
                    243
                ], 
                [
                    977, 
                    244
                ], 
                [
                    983, 
                    252
                ], 
                [
                    980, 
                    267
                ], 
                [
                    984, 
                    275
                ], 
                [
                    989, 
                    273
                ], 
                [
                    998, 
                    273
                ], 
                [
                    999, 
                    266
                ], 
                [
                    998, 
                    257
                ], 
                [
                    995, 
                    250
                ], 
                [
                    994, 
                    236
                ], 
                [
                    1003, 
                    224
                ], 
                [
                    1005, 
                    211
                ], 
                [
                    1005, 
                    192
                ], 
                [
                    995, 
                    160
                ], 
                [
                    998, 
                    150
                ], 
                [
                    998, 
                    140
                ], 
                [
                    1008, 
                    122
                ], 
                [
                    1016, 
                    116
                ], 
                [
                    1036, 
                    110
                ], 
                [
                    1040, 
                    97
                ], 
                [
                    1041, 
                    77
                ], 
                [
                    1041, 
                    57
                ], 
                [
                    1045, 
                    38
                ], 
                [
                    1056, 
                    19
                ], 
                [
                    1077, 
                    12
                ], 
                [
                    1104, 
                    18
                ], 
                [
                    1115, 
                    34
                ], 
                [
                    1124, 
                    47
                ], 
                [
                    1133, 
                    52
                ], 
                [
                    1141, 
                    55
                ], 
                [
                    1153, 
                    73
                ], 
                [
                    1148, 
                    79
                ], 
                [
                    1139, 
                    92
                ], 
                [
                    1144, 
                    99
                ], 
                [
                    1145, 
                    106
                ], 
                [
                    1154, 
                    109
                ], 
                [
                    1168, 
                    124
                ], 
                [
                    1172, 
                    139
                ], 
                [
                    1168, 
                    156
                ], 
                [
                    1165, 
                    164
                ], 
                [
                    1166, 
                    177
                ], 
                [
                    1167, 
                    195
                ], 
                [
                    1187, 
                    209
                ], 
                [
                    1196, 
                    220
                ], 
                [
                    1196, 
                    245
                ], 
                [
                    1194, 
                    271
                ], 
                [
                    1213, 
                    338
                ], 
                [
                    1222, 
                    344
                ], 
                [
                    1227, 
                    355
                ], 
                [
                    1224, 
                    386
                ], 
                [
                    1211, 
                    394
                ], 
                [
                    1194, 
                    400
                ], 
                [
                    1171, 
                    402
                ], 
                [
                    1164, 
                    410
                ], 
                [
                    1164, 
                    431
                ], 
                [
                    1146, 
                    441
                ], 
                [
                    843, 
                    438
                ]
            ]
        }, 
        {
            "label": "road", 
            "polygon": [
                [
                    -2, 
                    708
                ], 
                [
                    997, 
                    440
                ], 
                [
                    1146, 
                    440
                ], 
                [
                    2045, 
                    640
                ], 
                [
                    2044, 
                    1022
                ], 
                [
                    -2, 
                    1020
                ]
            ]
        }, 
        {
            "label": "sidewalk", 
            "polygon": [
                [
                    270, 
                    503
                ], 
                [
                    878, 
                    448
                ], 
                [
                    911, 
                    448
                ], 
                [
                    902, 
                    471
                ], 
                [
                    887, 
                    475
                ], 
                [
                    742, 
                    524
                ], 
                [
                    576, 
                    576
                ], 
                [
                    545, 
                    596
                ], 
                [
                    485, 
                    619
                ]
            ]
        }, 
        {
            "label": "sidewalk", 
            "polygon": [
                [
                    1693, 
                    468
                ], 
                [
                    1995, 
                    495
                ], 
                [
                    1957, 
                    594
                ], 
                [
                    1640, 
                    505
                ]
            ]
        }, 
        {
            "label": "building", 
            "polygon": [
                [
                    1, 
                    1
                ], 
                [
                    872, 
                    0
                ], 
                [
                    868, 
                    299
                ], 
                [
                    863, 
                    316
                ], 
                [
                    856, 
                    448
                ], 
                [
                    741, 
                    469
                ], 
                [
                    638, 
                    493
                ], 
                [
                    482, 
                    519
                ], 
                [
                    -2, 
                    568
                ]
            ]
        }, 
        {
            "label": "building", 
            "polygon": [
                [
                    1347, 
                    31
                ], 
                [
                    1346, 
                    0
                ], 
                [
                    2044, 
                    0
                ], 
                [
                    2044, 
                    535
                ], 
                [
                    1888, 
                    511
                ], 
                [
                    1888, 
                    501
                ], 
                [
                    1835, 
                    502
                ], 
                [
                    1812, 
                    505
                ], 
                [
                    1715, 
                    498
                ], 
                [
                    1353, 
                    404
                ], 
                [
                    1355, 
                    340
                ], 
                [
                    1347, 
                    84
                ], 
                [
                    1347, 
                    50
                ]
            ]
        }, 
        {
            "label": "pole", 
            "polygon": [
                [
                    1178, 
                    351
                ], 
                [
                    1177, 
                    419
                ], 
                [
                    1181, 
                    423
                ], 
                [
                    1181, 
                    342
                ]
            ]
        }, 
        {
            "label": "pole", 
            "polygon": [
                [
                    1164, 
                    386
                ], 
                [
                    1163, 
                    427
                ], 
                [
                    1166, 
                    428
                ], 
                [
                    1167, 
                    372
                ]
            ]
        }, 
        {
            "label": "traffic sign", 
            "polygon": [
                [
                    1151, 
                    375
                ], 
                [
                    1166, 
                    350
                ], 
                [
                    1180, 
                    374
                ], 
                [
                    1165, 
                    376
                ]
            ]
        }, 
        {
            "label": "traffic sign", 
            "polygon": [
                [
                    1157, 
                    376
                ], 
                [
                    1176, 
                    374
                ], 
                [
                    1176, 
                    394
                ], 
                [
                    1156, 
                    394
                ]
            ]
        }, 
        {
            "label": "terrain", 
            "polygon": [
                [
                    1162, 
                    453
                ], 
                [
                    1135, 
                    453
                ], 
                [
                    1133, 
                    449
                ], 
                [
                    1134, 
                    445
                ], 
                [
                    1143, 
                    441
                ], 
                [
                    1168, 
                    441
                ], 
                [
                    1169, 
                    455
                ]
            ]
        }, 
        {
            "label": "static", 
            "polygon": [
                [
                    1139, 
                    427
                ], 
                [
                    1162, 
                    427
                ], 
                [
                    1160, 
                    445
                ], 
                [
                    1138, 
                    443
                ]
            ]
        }, 
        {
            "label": "traffic light", 
            "polygon": [
                [
                    1097, 
                    291
                ], 
                [
                    1124, 
                    291
                ], 
                [
                    1124, 
                    300
                ], 
                [
                    1099, 
                    301
                ]
            ]
        }, 
        {
            "label": "pole", 
            "polygon": [
                [
                    1054, 
                    443
                ], 
                [
                    1056, 
                    313
                ], 
                [
                    1058, 
                    303
                ], 
                [
                    1072, 
                    292
                ], 
                [
                    1100, 
                    289
                ], 
                [
                    1109, 
                    290
                ], 
                [
                    1109, 
                    294
                ], 
                [
                    1081, 
                    296
                ], 
                [
                    1075, 
                    296
                ], 
                [
                    1065, 
                    303
                ], 
                [
                    1063, 
                    313
                ], 
                [
                    1060, 
                    439
                ]
            ]
        }, 
        {
            "label": "traffic sign", 
            "polygon": [
                [
                    1067, 
                    361
                ], 
                [
                    1067, 
                    379
                ], 
                [
                    1057, 
                    378
                ], 
                [
                    1057, 
                    361
                ]
            ]
        }, 
        {
            "label": "pole", 
            "polygon": [
                [
                    1026, 
                    370
                ], 
                [
                    1025, 
                    443
                ], 
                [
                    1030, 
                    444
                ], 
                [
                    1029, 
                    371
                ]
            ]
        }, 
        {
            "label": "traffic sign", 
            "polygon": [
                [
                    1023, 
                    376
                ], 
                [
                    1020, 
                    368
                ], 
                [
                    1021, 
                    362
                ], 
                [
                    1026, 
                    361
                ], 
                [
                    1030, 
                    361
                ], 
                [
                    1036, 
                    366
                ], 
                [
                    1036, 
                    370
                ], 
                [
                    1029, 
                    378
                ]
            ]
        }, 
        {
            "label": "pole", 
            "polygon": [
                [
                    948, 
                    373
                ], 
                [
                    947, 
                    394
                ], 
                [
                    950, 
                    396
                ], 
                [
                    951, 
                    365
                ]
            ]
        }, 
        {
            "label": "traffic sign", 
            "polygon": [
                [
                    939, 
                    359
                ], 
                [
                    959, 
                    359
                ], 
                [
                    959, 
                    379
                ], 
                [
                    939, 
                    378
                ]
            ]
        }, 
        {
            "label": "car", 
            "polygon": [
                [
                    960, 
                    407
                ], 
                [
                    979, 
                    408
                ], 
                [
                    980, 
                    404
                ], 
                [
                    988, 
                    403
                ], 
                [
                    990, 
                    409
                ], 
                [
                    997, 
                    419
                ], 
                [
                    999, 
                    419
                ], 
                [
                    1002, 
                    422
                ], 
                [
                    1002, 
                    435
                ], 
                [
                    1002, 
                    460
                ], 
                [
                    992, 
                    461
                ], 
                [
                    993, 
                    456
                ], 
                [
                    977, 
                    453
                ]
            ]
        }, 
        {
            "label": "car", 
            "polygon": [
                [
                    901, 
                    395
                ], 
                [
                    926, 
                    390
                ], 
                [
                    960, 
                    390
                ], 
                [
                    970, 
                    403
                ], 
                [
                    978, 
                    416
                ], 
                [
                    985, 
                    419
                ], 
                [
                    982, 
                    425
                ], 
                [
                    984, 
                    436
                ], 
                [
                    985, 
                    458
                ], 
                [
                    985, 
                    464
                ], 
                [
                    981, 
                    468
                ], 
                [
                    976, 
                    470
                ], 
                [
                    968, 
                    470
                ], 
                [
                    964, 
                    467
                ], 
                [
                    943, 
                    465
                ], 
                [
                    921, 
                    466
                ], 
                [
                    921, 
                    472
                ], 
                [
                    900, 
                    474
                ], 
                [
                    897, 
                    460
                ], 
                [
                    896, 
                    435
                ], 
                [
                    897, 
                    411
                ], 
                [
                    897, 
                    402
                ]
            ]
        }, 
        {
            "label": "car", 
            "polygon": [
                [
                    771, 
                    404
                ], 
                [
                    804, 
                    401
                ], 
                [
                    835, 
                    399
                ], 
                [
                    857, 
                    399
                ], 
                [
                    870, 
                    405
                ], 
                [
                    884, 
                    425
                ], 
                [
                    893, 
                    426
                ], 
                [
                    895, 
                    439
                ], 
                [
                    895, 
                    443
                ], 
                [
                    899, 
                    467
                ], 
                [
                    899, 
                    489
                ], 
                [
                    900, 
                    507
                ], 
                [
                    895, 
                    512
                ], 
                [
                    885, 
                    513
                ], 
                [
                    877, 
                    521
                ], 
                [
                    865, 
                    520
                ], 
                [
                    857, 
                    508
                ], 
                [
                    818, 
                    511
                ], 
                [
                    788, 
                    511
                ], 
                [
                    787, 
                    516
                ], 
                [
                    772, 
                    518
                ], 
                [
                    767, 
                    516
                ], 
                [
                    759, 
                    516
                ], 
                [
                    760, 
                    528
                ], 
                [
                    739, 
                    528
                ], 
                [
                    736, 
                    509
                ], 
                [
                    734, 
                    481
                ], 
                [
                    744, 
                    449
                ], 
                [
                    732, 
                    448
                ], 
                [
                    733, 
                    440
                ], 
                [
                    743, 
                    435
                ], 
                [
                    750, 
                    438
                ], 
                [
                    756, 
                    425
                ], 
                [
                    762, 
                    416
                ]
            ]
        }, 
        {
            "label": "dynamic", 
            "polygon": [
                [
                    590, 
                    437
                ], 
                [
                    606, 
                    426
                ], 
                [
                    621, 
                    426
                ], 
                [
                    650, 
                    433
                ], 
                [
                    642, 
                    445
                ], 
                [
                    636, 
                    487
                ], 
                [
                    644, 
                    488
                ], 
                [
                    639, 
                    503
                ], 
                [
                    624, 
                    504
                ], 
                [
                    594, 
                    502
                ], 
                [
                    597, 
                    465
                ], 
                [
                    597, 
                    445
                ]
            ]
        }, 
        {
            "label": "car", 
            "polygon": [
                [
                    20, 
                    342
                ], 
                [
                    105, 
                    341
                ], 
                [
                    177, 
                    340
                ], 
                [
                    257, 
                    341
                ], 
                [
                    307, 
                    348
                ], 
                [
                    349, 
                    360
                ], 
                [
                    383, 
                    396
                ], 
                [
                    418, 
                    440
                ], 
                [
                    430, 
                    457
                ], 
                [
                    427, 
                    440
                ], 
                [
                    437, 
                    437
                ], 
                [
                    458, 
                    438
                ], 
                [
                    474, 
                    444
                ], 
                [
                    476, 
                    454
                ], 
                [
                    476, 
                    466
                ], 
                [
                    458, 
                    471
                ], 
                [
                    439, 
                    475
                ], 
                [
                    465, 
                    494
                ], 
                [
                    482, 
                    506
                ], 
                [
                    498, 
                    534
                ], 
                [
                    511, 
                    569
                ], 
                [
                    512, 
                    620
                ], 
                [
                    513, 
                    649
                ], 
                [
                    510, 
                    680
                ], 
                [
                    505, 
                    705
                ], 
                [
                    490, 
                    715
                ], 
                [
                    451, 
                    714
                ], 
                [
                    443, 
                    691
                ], 
                [
                    443, 
                    674
                ], 
                [
                    390, 
                    698
                ], 
                [
                    325, 
                    722
                ], 
                [
                    322, 
                    747
                ], 
                [
                    320, 
                    776
                ], 
                [
                    306, 
                    808
                ], 
                [
                    274, 
                    822
                ], 
                [
                    225, 
                    820
                ], 
                [
                    213, 
                    796
                ], 
                [
                    206, 
                    757
                ], 
                [
                    130, 
                    782
                ], 
                [
                    -2, 
                    795
                ], 
                [
                    0, 
                    348
                ], 
                [
                    9, 
                    342
                ]
            ]
        }, 
        {
            "label": "vegetation", 
            "polygon": [
                [
                    1238, 
                    417
                ], 
                [
                    1239, 
                    405
                ], 
                [
                    1228, 
                    394
                ], 
                [
                    1225, 
                    392
                ], 
                [
                    1209, 
                    378
                ], 
                [
                    1191, 
                    359
                ], 
                [
                    1176, 
                    352
                ], 
                [
                    1161, 
                    342
                ], 
                [
                    1152, 
                    320
                ], 
                [
                    1144, 
                    315
                ], 
                [
                    1134, 
                    299
                ], 
                [
                    1134, 
                    285
                ], 
                [
                    1143, 
                    274
                ], 
                [
                    1152, 
                    262
                ], 
                [
                    1161, 
                    258
                ], 
                [
                    1172, 
                    257
                ], 
                [
                    1187, 
                    248
                ], 
                [
                    1194, 
                    244
                ], 
                [
                    1195, 
                    240
                ], 
                [
                    1192, 
                    236
                ], 
                [
                    1206, 
                    228
                ], 
                [
                    1219, 
                    228
                ], 
                [
                    1234, 
                    214
                ], 
                [
                    1244, 
                    202
                ], 
                [
                    1234, 
                    189
                ], 
                [
                    1212, 
                    179
                ], 
                [
                    1197, 
                    172
                ], 
                [
                    1181, 
                    166
                ], 
                [
                    1181, 
                    151
                ], 
                [
                    1210, 
                    127
                ], 
                [
                    1226, 
                    123
                ], 
                [
                    1239, 
                    121
                ], 
                [
                    1240, 
                    111
                ], 
                [
                    1260, 
                    103
                ], 
                [
                    1269, 
                    109
                ], 
                [
                    1281, 
                    103
                ], 
                [
                    1292, 
                    100
                ], 
                [
                    1301, 
                    102
                ], 
                [
                    1313, 
                    102
                ], 
                [
                    1319, 
                    100
                ], 
                [
                    1340, 
                    73
                ], 
                [
                    1346, 
                    66
                ], 
                [
                    1347, 
                    51
                ], 
                [
                    1363, 
                    32
                ], 
                [
                    1359, 
                    23
                ], 
                [
                    1347, 
                    13
                ], 
                [
                    1346, 
                    0
                ], 
                [
                    1441, 
                    2
                ], 
                [
                    1444, 
                    8
                ], 
                [
                    1458, 
                    15
                ], 
                [
                    1461, 
                    24
                ], 
                [
                    1479, 
                    69
                ], 
                [
                    1481, 
                    62
                ], 
                [
                    1486, 
                    53
                ], 
                [
                    1496, 
                    54
                ], 
                [
                    1508, 
                    71
                ], 
                [
                    1520, 
                    76
                ], 
                [
                    1537, 
                    73
                ], 
                [
                    1546, 
                    73
                ], 
                [
                    1562, 
                    70
                ], 
                [
                    1568, 
                    54
                ], 
                [
                    1575, 
                    48
                ], 
                [
                    1587, 
                    59
                ], 
                [
                    1600, 
                    72
                ], 
                [
                    1607, 
                    103
                ], 
                [
                    1607, 
                    110
                ], 
                [
                    1617, 
                    120
                ], 
                [
                    1622, 
                    192
                ], 
                [
                    1624, 
                    209
                ], 
                [
                    1626, 
                    238
                ], 
                [
                    1616, 
                    249
                ], 
                [
                    1607, 
                    256
                ], 
                [
                    1608, 
                    259
                ], 
                [
                    1615, 
                    262
                ], 
                [
                    1621, 
                    269
                ], 
                [
                    1618, 
                    285
                ], 
                [
                    1603, 
                    294
                ], 
                [
                    1590, 
                    302
                ], 
                [
                    1588, 
                    307
                ], 
                [
                    1574, 
                    316
                ], 
                [
                    1550, 
                    325
                ], 
                [
                    1523, 
                    331
                ], 
                [
                    1513, 
                    335
                ], 
                [
                    1503, 
                    351
                ], 
                [
                    1485, 
                    358
                ], 
                [
                    1493, 
                    365
                ], 
                [
                    1486, 
                    376
                ], 
                [
                    1476, 
                    385
                ], 
                [
                    1476, 
                    410
                ], 
                [
                    1412, 
                    402
                ], 
                [
                    1409, 
                    364
                ], 
                [
                    1405, 
                    358
                ], 
                [
                    1394, 
                    360
                ], 
                [
                    1392, 
                    365
                ], 
                [
                    1387, 
                    368
                ], 
                [
                    1375, 
                    375
                ], 
                [
                    1372, 
                    402
                ], 
                [
                    1357, 
                    402
                ], 
                [
                    1358, 
                    391
                ], 
                [
                    1360, 
                    383
                ], 
                [
                    1360, 
                    379
                ], 
                [
                    1356, 
                    374
                ], 
                [
                    1348, 
                    374
                ], 
                [
                    1342, 
                    374
                ], 
                [
                    1336, 
                    379
                ], 
                [
                    1331, 
                    386
                ], 
                [
                    1326, 
                    390
                ], 
                [
                    1322, 
                    405
                ], 
                [
                    1302, 
                    411
                ], 
                [
                    1302, 
                    387
                ], 
                [
                    1301, 
                    382
                ], 
                [
                    1295, 
                    385
                ], 
                [
                    1279, 
                    381
                ], 
                [
                    1265, 
                    387
                ], 
                [
                    1259, 
                    393
                ], 
                [
                    1255, 
                    413
                ]
            ]
        }, 
        {
            "label": "car", 
            "polygon": [
                [
                    1178, 
                    409
                ], 
                [
                    1187, 
                    410
                ], 
                [
                    1217, 
                    409
                ], 
                [
                    1226, 
                    427
                ], 
                [
                    1211, 
                    463
                ], 
                [
                    1201, 
                    462
                ], 
                [
                    1199, 
                    458
                ], 
                [
                    1179, 
                    458
                ], 
                [
                    1173, 
                    461
                ], 
                [
                    1153, 
                    455
                ], 
                [
                    1153, 
                    442
                ], 
                [
                    1156, 
                    427
                ], 
                [
                    1162, 
                    419
                ], 
                [
                    1172, 
                    410
                ]
            ]
        }, 
        {
            "label": "car", 
            "polygon": [
                [
                    1228, 
                    407
                ], 
                [
                    1243, 
                    405
                ], 
                [
                    1254, 
                    405
                ], 
                [
                    1228, 
                    484
                ], 
                [
                    1220, 
                    482
                ], 
                [
                    1212, 
                    480
                ], 
                [
                    1203, 
                    477
                ], 
                [
                    1201, 
                    452
                ], 
                [
                    1208, 
                    432
                ], 
                [
                    1204, 
                    433
                ], 
                [
                    1205, 
                    425
                ], 
                [
                    1216, 
                    423
                ], 
                [
                    1225, 
                    414
                ]
            ]
        }, 
        {
            "label": "car", 
            "polygon": [
                [
                    1261, 
                    401
                ], 
                [
                    1284, 
                    402
                ], 
                [
                    1308, 
                    405
                ], 
                [
                    1321, 
                    406
                ], 
                [
                    1332, 
                    419
                ], 
                [
                    1289, 
                    488
                ], 
                [
                    1248, 
                    487
                ], 
                [
                    1245, 
                    495
                ], 
                [
                    1234, 
                    491
                ], 
                [
                    1223, 
                    487
                ], 
                [
                    1222, 
                    472
                ], 
                [
                    1222, 
                    452
                ], 
                [
                    1225, 
                    439
                ], 
                [
                    1223, 
                    434
                ], 
                [
                    1225, 
                    425
                ], 
                [
                    1230, 
                    424
                ], 
                [
                    1234, 
                    429
                ], 
                [
                    1239, 
                    419
                ], 
                [
                    1252, 
                    403
                ]
            ]
        }, 
        {
            "label": "car", 
            "polygon": [
                [
                    1306, 
                    435
                ], 
                [
                    1324, 
                    421
                ], 
                [
                    1342, 
                    410
                ], 
                [
                    1353, 
                    410
                ], 
                [
                    1304, 
                    509
                ], 
                [
                    1294, 
                    500
                ], 
                [
                    1289, 
                    496
                ], 
                [
                    1285, 
                    480
                ], 
                [
                    1292, 
                    472
                ], 
                [
                    1290, 
                    455
                ], 
                [
                    1295, 
                    448
                ], 
                [
                    1297, 
                    444
                ], 
                [
                    1299, 
                    442
                ]
            ]
        }, 
        {
            "label": "dynamic", 
            "polygon": [
                [
                    1282, 
                    438
                ], 
                [
                    1293, 
                    443
                ], 
                [
                    1285, 
                    454
                ], 
                [
                    1283, 
                    497
                ], 
                [
                    1286, 
                    502
                ], 
                [
                    1286, 
                    512
                ], 
                [
                    1279, 
                    518
                ], 
                [
                    1245, 
                    516
                ], 
                [
                    1247, 
                    494
                ], 
                [
                    1246, 
                    461
                ], 
                [
                    1243, 
                    454
                ], 
                [
                    1240, 
                    449
                ], 
                [
                    1240, 
                    443
                ], 
                [
                    1247, 
                    438
                ]
            ]
        }, 
        {
            "label": "car", 
            "polygon": [
                [
                    1494, 
                    400
                ], 
                [
                    1526, 
                    398
                ], 
                [
                    1559, 
                    395
                ], 
                [
                    1592, 
                    393
                ], 
                [
                    1611, 
                    401
                ], 
                [
                    1618, 
                    404
                ], 
                [
                    1646, 
                    429
                ], 
                [
                    1656, 
                    447
                ], 
                [
                    1587, 
                    450
                ]
            ]
        }, 
        {
            "label": "car", 
            "polygon": [
                [
                    1483, 
                    410
                ], 
                [
                    1509, 
                    405
                ], 
                [
                    1522, 
                    407
                ], 
                [
                    1551, 
                    413
                ], 
                [
                    1599, 
                    439
                ], 
                [
                    1619, 
                    439
                ], 
                [
                    1672, 
                    447
                ], 
                [
                    1698, 
                    454
                ], 
                [
                    1715, 
                    463
                ], 
                [
                    1730, 
                    505
                ], 
                [
                    1725, 
                    513
                ], 
                [
                    1694, 
                    516
                ], 
                [
                    1495, 
                    523
                ]
            ]
        }, 
        {
            "label": "car", 
            "polygon": [
                [
                    1381, 
                    393
                ], 
                [
                    1442, 
                    395
                ], 
                [
                    1480, 
                    398
                ], 
                [
                    1496, 
                    400
                ], 
                [
                    1523, 
                    427
                ], 
                [
                    1536, 
                    449
                ], 
                [
                    1510, 
                    526
                ], 
                [
                    1491, 
                    548
                ], 
                [
                    1474, 
                    556
                ], 
                [
                    1447, 
                    550
                ], 
                [
                    1436, 
                    534
                ], 
                [
                    1411, 
                    535
                ], 
                [
                    1386, 
                    534
                ], 
                [
                    1377, 
                    554
                ], 
                [
                    1360, 
                    554
                ], 
                [
                    1346, 
                    550
                ], 
                [
                    1346, 
                    528
                ], 
                [
                    1338, 
                    526
                ], 
                [
                    1330, 
                    538
                ], 
                [
                    1303, 
                    535
                ], 
                [
                    1292, 
                    521
                ], 
                [
                    1292, 
                    498
                ], 
                [
                    1301, 
                    483
                ], 
                [
                    1307, 
                    465
                ], 
                [
                    1317, 
                    448
                ], 
                [
                    1303, 
                    447
                ], 
                [
                    1300, 
                    439
                ], 
                [
                    1305, 
                    433
                ], 
                [
                    1321, 
                    434
                ], 
                [
                    1325, 
                    435
                ], 
                [
                    1328, 
                    435
                ], 
                [
                    1342, 
                    417
                ], 
                [
                    1356, 
                    401
                ], 
                [
                    1362, 
                    397
                ], 
                [
                    1368, 
                    395
                ]
            ]
        }, 
        {
            "label": "dynamic", 
            "polygon": [
                [
                    1408, 
                    554
                ], 
                [
                    1419, 
                    556
                ], 
                [
                    1430, 
                    563
                ], 
                [
                    1433, 
                    570
                ], 
                [
                    1431, 
                    576
                ], 
                [
                    1332, 
                    571
                ], 
                [
                    1326, 
                    565
                ], 
                [
                    1328, 
                    555
                ], 
                [
                    1334, 
                    552
                ], 
                [
                    1348, 
                    555
                ], 
                [
                    1365, 
                    557
                ], 
                [
                    1385, 
                    558
                ], 
                [
                    1400, 
                    556
                ]
            ]
        }, 
        {
            "label": "terrain", 
            "polygon": [
                [
                    1859, 
                    541
                ], 
                [
                    1800, 
                    641
                ], 
                [
                    1530, 
                    559
                ], 
                [
                    1524, 
                    515
                ], 
                [
                    1698, 
                    513
                ], 
                [
                    1850, 
                    536
                ]
            ]
        }, 
        {
            "label": "vegetation", 
            "polygon": [
                [
                    1731, 
                    288
                ], 
                [
                    1711, 
                    275
                ], 
                [
                    1692, 
                    271
                ], 
                [
                    1675, 
                    260
                ], 
                [
                    1673, 
                    249
                ], 
                [
                    1662, 
                    237
                ], 
                [
                    1656, 
                    251
                ], 
                [
                    1641, 
                    256
                ], 
                [
                    1605, 
                    248
                ], 
                [
                    1567, 
                    227
                ], 
                [
                    1563, 
                    190
                ], 
                [
                    1564, 
                    144
                ], 
                [
                    1586, 
                    129
                ], 
                [
                    1627, 
                    120
                ], 
                [
                    1629, 
                    106
                ], 
                [
                    1610, 
                    89
                ], 
                [
                    1598, 
                    75
                ], 
                [
                    1600, 
                    67
                ], 
                [
                    1611, 
                    59
                ], 
                [
                    1627, 
                    59
                ], 
                [
                    1636, 
                    51
                ], 
                [
                    1629, 
                    37
                ], 
                [
                    1606, 
                    36
                ], 
                [
                    1597, 
                    30
                ], 
                [
                    1569, 
                    33
                ], 
                [
                    1515, 
                    33
                ], 
                [
                    1501, 
                    26
                ], 
                [
                    1505, 
                    9
                ], 
                [
                    1507, 
                    1
                ], 
                [
                    2041, 
                    4
                ], 
                [
                    2045, 
                    278
                ], 
                [
                    2041, 
                    295
                ], 
                [
                    2033, 
                    308
                ], 
                [
                    2033, 
                    352
                ], 
                [
                    2038, 
                    446
                ], 
                [
                    2040, 
                    483
                ], 
                [
                    2008, 
                    507
                ], 
                [
                    2008, 
                    477
                ], 
                [
                    2001, 
                    410
                ], 
                [
                    1993, 
                    332
                ], 
                [
                    1977, 
                    303
                ], 
                [
                    1962, 
                    255
                ], 
                [
                    1952, 
                    232
                ], 
                [
                    1945, 
                    212
                ], 
                [
                    1932, 
                    196
                ], 
                [
                    1907, 
                    180
                ], 
                [
                    1889, 
                    178
                ], 
                [
                    1893, 
                    192
                ], 
                [
                    1891, 
                    204
                ], 
                [
                    1868, 
                    210
                ], 
                [
                    1838, 
                    198
                ], 
                [
                    1823, 
                    205
                ], 
                [
                    1798, 
                    210
                ], 
                [
                    1790, 
                    226
                ], 
                [
                    1796, 
                    236
                ], 
                [
                    1813, 
                    236
                ], 
                [
                    1831, 
                    243
                ], 
                [
                    1848, 
                    261
                ], 
                [
                    1849, 
                    275
                ], 
                [
                    1846, 
                    281
                ], 
                [
                    1834, 
                    278
                ], 
                [
                    1820, 
                    266
                ], 
                [
                    1807, 
                    265
                ], 
                [
                    1803, 
                    275
                ], 
                [
                    1794, 
                    278
                ], 
                [
                    1767, 
                    289
                ], 
                [
                    1755, 
                    298
                ], 
                [
                    1749, 
                    306
                ], 
                [
                    1754, 
                    307
                ], 
                [
                    1765, 
                    317
                ], 
                [
                    1764, 
                    339
                ], 
                [
                    1758, 
                    374
                ], 
                [
                    1750, 
                    395
                ], 
                [
                    1766, 
                    385
                ], 
                [
                    1802, 
                    366
                ], 
                [
                    1794, 
                    381
                ], 
                [
                    1767, 
                    402
                ], 
                [
                    1755, 
                    412
                ], 
                [
                    1756, 
                    428
                ], 
                [
                    1754, 
                    448
                ], 
                [
                    1759, 
                    466
                ], 
                [
                    1757, 
                    477
                ], 
                [
                    1752, 
                    488
                ], 
                [
                    1751, 
                    501
                ], 
                [
                    1743, 
                    557
                ], 
                [
                    1726, 
                    554
                ], 
                [
                    1725, 
                    487
                ], 
                [
                    1719, 
                    466
                ], 
                [
                    1711, 
                    448
                ], 
                [
                    1706, 
                    434
                ], 
                [
                    1701, 
                    409
                ], 
                [
                    1713, 
                    394
                ], 
                [
                    1716, 
                    392
                ], 
                [
                    1718, 
                    371
                ], 
                [
                    1725, 
                    365
                ], 
                [
                    1731, 
                    354
                ], 
                [
                    1732, 
                    327
                ], 
                [
                    1732, 
                    303
                ]
            ]
        }, 
        {
            "label": "fence", 
            "polygon": [
                [
                    1529, 
                    495
                ], 
                [
                    1723, 
                    497
                ], 
                [
                    1724, 
                    524
                ], 
                [
                    1723, 
                    521
                ], 
                [
                    1722, 
                    501
                ], 
                [
                    1660, 
                    502
                ], 
                [
                    1658, 
                    521
                ], 
                [
                    1650, 
                    519
                ], 
                [
                    1650, 
                    503
                ], 
                [
                    1547, 
                    501
                ], 
                [
                    1813, 
                    551
                ], 
                [
                    1808, 
                    558
                ], 
                [
                    1744, 
                    548
                ], 
                [
                    1741, 
                    583
                ], 
                [
                    1731, 
                    579
                ], 
                [
                    1734, 
                    550
                ], 
                [
                    1665, 
                    531
                ], 
                [
                    1665, 
                    562
                ], 
                [
                    1655, 
                    557
                ], 
                [
                    1658, 
                    532
                ], 
                [
                    1605, 
                    519
                ], 
                [
                    1604, 
                    545
                ], 
                [
                    1599, 
                    542
                ], 
                [
                    1598, 
                    520
                ], 
                [
                    1556, 
                    510
                ], 
                [
                    1555, 
                    533
                ], 
                [
                    1548, 
                    530
                ], 
                [
                    1550, 
                    510
                ]
            ]
        }, 
        {
            "label": "motorcycle", 
            "polygon": [
                [
                    1424, 
                    428
                ], 
                [
                    1452, 
                    419
                ], 
                [
                    1466, 
                    420
                ], 
                [
                    1471, 
                    427
                ], 
                [
                    1477, 
                    427
                ], 
                [
                    1477, 
                    420
                ], 
                [
                    1483, 
                    410
                ], 
                [
                    1486, 
                    402
                ], 
                [
                    1480, 
                    393
                ], 
                [
                    1495, 
                    388
                ], 
                [
                    1508, 
                    384
                ], 
                [
                    1522, 
                    384
                ], 
                [
                    1527, 
                    388
                ], 
                [
                    1528, 
                    397
                ], 
                [
                    1524, 
                    412
                ], 
                [
                    1520, 
                    422
                ], 
                [
                    1533, 
                    433
                ], 
                [
                    1539, 
                    437
                ], 
                [
                    1545, 
                    438
                ], 
                [
                    1552, 
                    430
                ], 
                [
                    1558, 
                    427
                ], 
                [
                    1574, 
                    429
                ], 
                [
                    1579, 
                    438
                ], 
                [
                    1572, 
                    448
                ], 
                [
                    1580, 
                    487
                ], 
                [
                    1540, 
                    497
                ], 
                [
                    1540, 
                    504
                ], 
                [
                    1543, 
                    509
                ], 
                [
                    1538, 
                    529
                ], 
                [
                    1541, 
                    536
                ], 
                [
                    1543, 
                    545
                ], 
                [
                    1540, 
                    562
                ], 
                [
                    1537, 
                    586
                ], 
                [
                    1528, 
                    589
                ], 
                [
                    1511, 
                    583
                ], 
                [
                    1501, 
                    560
                ], 
                [
                    1495, 
                    558
                ], 
                [
                    1492, 
                    564
                ], 
                [
                    1481, 
                    570
                ], 
                [
                    1476, 
                    565
                ], 
                [
                    1462, 
                    577
                ], 
                [
                    1455, 
                    577
                ], 
                [
                    1463, 
                    556
                ], 
                [
                    1453, 
                    530
                ], 
                [
                    1447, 
                    521
                ], 
                [
                    1433, 
                    525
                ], 
                [
                    1424, 
                    488
                ], 
                [
                    1420, 
                    459
                ], 
                [
                    1420, 
                    441
                ]
            ]
        }, 
        {
            "label": "person", 
            "polygon": [
                [
                    1402, 
                    377
                ], 
                [
                    1402, 
                    367
                ], 
                [
                    1405, 
                    360
                ], 
                [
                    1411, 
                    356
                ], 
                [
                    1422, 
                    357
                ], 
                [
                    1427, 
                    361
                ], 
                [
                    1432, 
                    370
                ], 
                [
                    1432, 
                    375
                ], 
                [
                    1437, 
                    381
                ], 
                [
                    1447, 
                    393
                ], 
                [
                    1454, 
                    408
                ], 
                [
                    1455, 
                    421
                ], 
                [
                    1438, 
                    428
                ], 
                [
                    1433, 
                    429
                ], 
                [
                    1432, 
                    444
                ], 
                [
                    1428, 
                    458
                ], 
                [
                    1429, 
                    473
                ], 
                [
                    1428, 
                    492
                ], 
                [
                    1423, 
                    513
                ], 
                [
                    1416, 
                    547
                ], 
                [
                    1413, 
                    557
                ], 
                [
                    1413, 
                    563
                ], 
                [
                    1421, 
                    570
                ], 
                [
                    1429, 
                    573
                ], 
                [
                    1433, 
                    579
                ], 
                [
                    1433, 
                    582
                ], 
                [
                    1387, 
                    579
                ], 
                [
                    1387, 
                    560
                ], 
                [
                    1395, 
                    525
                ], 
                [
                    1398, 
                    510
                ], 
                [
                    1392, 
                    488
                ], 
                [
                    1383, 
                    474
                ], 
                [
                    1382, 
                    454
                ], 
                [
                    1384, 
                    434
                ], 
                [
                    1373, 
                    430
                ], 
                [
                    1377, 
                    412
                ], 
                [
                    1382, 
                    400
                ], 
                [
                    1385, 
                    390
                ], 
                [
                    1393, 
                    384
                ], 
                [
                    1394, 
                    382
                ]
            ]
        }, 
        {
            "label": "car", 
            "polygon": [
                [
                    1892, 
                    521
                ], 
                [
                    1963, 
                    504
                ], 
                [
                    2012, 
                    488
                ], 
                [
                    2045, 
                    466
                ], 
                [
                    2045, 
                    745
                ], 
                [
                    2025, 
                    746
                ], 
                [
                    1989, 
                    733
                ], 
                [
                    1971, 
                    703
                ], 
                [
                    1876, 
                    700
                ], 
                [
                    1820, 
                    685
                ], 
                [
                    1801, 
                    675
                ], 
                [
                    1790, 
                    650
                ], 
                [
                    1781, 
                    630
                ], 
                [
                    1781, 
                    604
                ], 
                [
                    1783, 
                    587
                ], 
                [
                    1802, 
                    548
                ], 
                [
                    1859, 
                    529
                ], 
                [
                    1883, 
                    524
                ]
            ]
        }, 
        {
            "label": "license plate", 
            "polygon": [
                [
                    776, 
                    480
                ], 
                [
                    823, 
                    477
                ], 
                [
                    825, 
                    489
                ], 
                [
                    776, 
                    491
                ]
            ]
        }, 
        {
            "label": "ego vehicle", 
            "polygon": [
                [
                    271, 
                    1023
                ], 
                [
                    387, 
                    1009
                ], 
                [
                    549, 
                    993
                ], 
                [
                    821, 
                    966
                ], 
                [
                    1082, 
                    950
                ], 
                [
                    1142, 
                    947
                ], 
                [
                    1112, 
                    932
                ], 
                [
                    1096, 
                    896
                ], 
                [
                    1108, 
                    861
                ], 
                [
                    1137, 
                    844
                ], 
                [
                    1175, 
                    844
                ], 
                [
                    1204, 
                    867
                ], 
                [
                    1209, 
                    897
                ], 
                [
                    1195, 
                    931
                ], 
                [
                    1161, 
                    945
                ], 
                [
                    1376, 
                    957
                ], 
                [
                    1654, 
                    977
                ], 
                [
                    1883, 
                    1002
                ], 
                [
                    2028, 
                    1023
                ]
            ]
        }, 
        {
            "label": "out of roi", 
            "polygon": [
                [
                    0, 
                    0
                ], 
                [
                    2048, 
                    0
                ], 
                [
                    2048, 
                    1024
                ], 
                [
                    0, 
                    1024
                ], 
                [
                    0, 
                    0
                ], 
                [
                    5, 
                    5
                ], 
                [
                    5, 
                    1019
                ], 
                [
                    2043, 
                    1019
                ], 
                [
                    2043, 
                    5
                ], 
                [
                    5, 
                    5
                ]
            ]
        }
    ]
}